odoo/addons/account_banking_sepa_credit_transfer/README.rst
odoo/addons/account_banking_sepa_credit_transfer/__init__.py
odoo/addons/account_banking_sepa_credit_transfer/__manifest__.py
odoo/addons/account_banking_sepa_credit_transfer/post_install.py
odoo/addons/account_banking_sepa_credit_transfer/data/account_payment_method.xml
odoo/addons/account_banking_sepa_credit_transfer/data/pain.001.001.02.xsd
odoo/addons/account_banking_sepa_credit_transfer/data/pain.001.001.03.xsd
odoo/addons/account_banking_sepa_credit_transfer/data/pain.001.001.04.xsd
odoo/addons/account_banking_sepa_credit_transfer/data/pain.001.001.05.xsd
odoo/addons/account_banking_sepa_credit_transfer/data/pain.001.003.03.xsd
odoo/addons/account_banking_sepa_credit_transfer/demo/sepa_credit_transfer_demo.xml
odoo/addons/account_banking_sepa_credit_transfer/i18n/account_banking_sepa_credit_transfer.pot
odoo/addons/account_banking_sepa_credit_transfer/i18n/de.po
odoo/addons/account_banking_sepa_credit_transfer/i18n/es.po
odoo/addons/account_banking_sepa_credit_transfer/i18n/es_AR.po
odoo/addons/account_banking_sepa_credit_transfer/i18n/fr.po
odoo/addons/account_banking_sepa_credit_transfer/i18n/fr_FR.po
odoo/addons/account_banking_sepa_credit_transfer/i18n/hr.po
odoo/addons/account_banking_sepa_credit_transfer/i18n/it.po
odoo/addons/account_banking_sepa_credit_transfer/i18n/nb_NO.po
odoo/addons/account_banking_sepa_credit_transfer/i18n/nl.po
odoo/addons/account_banking_sepa_credit_transfer/i18n/pt_BR.po
odoo/addons/account_banking_sepa_credit_transfer/i18n/sl.po
odoo/addons/account_banking_sepa_credit_transfer/i18n/sv.po
odoo/addons/account_banking_sepa_credit_transfer/migrations/14.0.2.0.3/post-migration.py
odoo/addons/account_banking_sepa_credit_transfer/models/__init__.py
odoo/addons/account_banking_sepa_credit_transfer/models/account_payment_line.py
odoo/addons/account_banking_sepa_credit_transfer/models/account_payment_method.py
odoo14_addon_account_banking_sepa_credit_transfer-14.0.2.0.4.dist-info/METADATA
odoo14_addon_account_banking_sepa_credit_transfer-14.0.2.0.4.dist-info/WHEEL
odoo14_addon_account_banking_sepa_credit_transfer-14.0.2.0.4.dist-info/top_level.txt
odoo14_addon_account_banking_sepa_credit_transfer-14.0.2.0.4.dist-info/RECORD
