Metadata-Version: 2.1
Name: odoo14-addon-account_banking_sepa_credit_transfer
Version: 14.0.2.0.4
Summary: Create SEPA XML files for Credit Transfers
Home-page: https://github.com/OCA/bank-payment
Author: Akretion, Tecnativa, Odoo Community Association (OCA)
Author-email: support@odoo-community.org
License: AGPL-3
Classifier: Programming Language :: Python
Classifier: Framework :: Odoo
Classifier: Framework :: Odoo :: 14.0
Classifier: License :: OSI Approved :: GNU Affero General Public License v3
Requires-Python: >=3.6
Requires-Dist: odoo14-addon-account-banking-pain-base
Requires-Dist: odoo <14.1dev,>=14.0a
